{
  "project_info": {
    "project_number": "466473133509",
    "project_id": "kitsmart-d776f",
    "storage_bucket": "kitsmart-d776f.appspot.com"
  },
  "client": [
    {
      "client_info": {
        "mobilesdk_app_id": "1:466473133509:android:c2346d1a34677f7ba3d7ac",
        "android_client_info": {
          "package_name": "com.example.flutter_application_2"
        }
      },
      "oauth_client": [],
      "api_key": [
        {
          "current_key": "AIzaSyBoBfqjYvpTF0rlYR36Y1cpi1tf1t4Gh_Y"
        }
      ],
      "services": {
        "appinvite_service": {
          "other_platform_oauth_client": []
        }
      }
    }
  ],
  "configuration_version": "1"
}